start_html_tag_helpers/__init__.py
start_html_tag_helpers/filter_attrs.py
start_html_tag_helpers/wrap_svg.py
start_html_tag_helpers-0.0.4.dist-info/LICENSE
start_html_tag_helpers-0.0.4.dist-info/METADATA
start_html_tag_helpers-0.0.4.dist-info/WHEEL
start_html_tag_helpers-0.0.4.dist-info/RECORD
