Metadata-Version: 2.1
Name: start-html-tag-helpers
Version: 0.0.4
Summary: Some utility functions for dealing with html attributes and tags.
Home-page: https://mv3.dev
License: MIT
Author: Marcelino G. Veloso III
Author-email: mars@veloso.one
Requires-Python: >=3.10,<4.0
Classifier: Development Status :: 4 - Beta
Classifier: Framework :: Pytest
Classifier: License :: OSI Approved :: MIT License
Classifier: Programming Language :: Python :: 3
Classifier: Programming Language :: Python :: 3.10
Classifier: Programming Language :: Python :: 3.11
Classifier: Programming Language :: Python :: 3.11
Classifier: Typing :: Typed
Requires-Dist: beautifulsoup4 (>=4.12.2,<5.0.0)
Project-URL: Documentation, https://mv3.dev/start-html-tag-helpers
Project-URL: Repository, https://github.com/justmars/start-html-tag-helpers
